mcp_knowledge_tools/__init__.py
mcp_knowledge_tools/server.py
mcp_knowledge_tools-0.1.0.dist-info/METADATA
mcp_knowledge_tools-0.1.0.dist-info/WHEEL
mcp_knowledge_tools-0.1.0.dist-info/entry_points.txt
mcp_knowledge_tools-0.1.0.dist-info/top_level.txt
mcp_knowledge_tools-0.1.0.dist-info/RECORD
