Metadata-Version: 2.4
Name: mcp-knowledge-tools
Version: 0.1.0
Summary: MCP server exposing internal knowledge retrieval tools.
Author-email: Generated <generated@example.com>
Requires-Python: >=3.10
Requires-Dist: mcp[cli]>=1.2.0
Requires-Dist: httpx>=0.26
Requires-Dist: beautifulsoup4>=4.12
Requires-Dist: lxml>=5.0
Requires-Dist: starlette>=0.37
Requires-Dist: uvicorn>=0.29
Requires-Dist: pydantic>=2.7
